basic_knn/__init__.py
basic_knn/classes.py
basic_knn/functions.py
basic_knn/knn.py
basic_knn/utils.py
basic_knn-0.0.2.dist-info/LICENSE
basic_knn-0.0.2.dist-info/METADATA
basic_knn-0.0.2.dist-info/WHEEL
basic_knn-0.0.2.dist-info/top_level.txt
basic_knn-0.0.2.dist-info/RECORD
