Metadata-Version: 2.1
Name: basic-knn
Version: 0.0.2
Summary: K-Nearest Neighbors algorithm for classification problems.
Home-page: https://github.com/Egesabanci/basic_knn
Author: Ege Sabancı
Author-email: egesabanci@outlook.com.tr
License: UNKNOWN
Download-URL: https://pypi.org/project/basic_knn
Platform: UNKNOWN
Classifier: Programming Language :: Python :: 3
Classifier: License :: OSI Approved :: MIT License
Classifier: Operating System :: OS Independent
Requires-Python: >=3.6
Requires-Dist: numpy
Requires-Dist: pandas
